_arv.so
arv/__init__.py
arv/__main__.py
arv/match.py
arv/traits.py
arv/util.py
arv-0.9.2.dist-info/DESCRIPTION.rst
arv-0.9.2.dist-info/METADATA
arv-0.9.2.dist-info/metadata.json
arv-0.9.2.dist-info/RECORD
arv-0.9.2.dist-info/top_level.txt
arv-0.9.2.dist-info/WHEEL
