Metadata-Version: 2.0
Name: arv
Version: 0.9.2
Summary: A fast 23andMe raw genome file parser
Home-page: https://github.com/cslarsen/arv
Author: Christian Stigen Larsen
Author-email: csl@csl.name
License: https://www.gnu.org/licenses/gpl-3.0.html
Keywords: 23andMe,bio,biology,biopython,disease,DNA,gene,genome,health,protein,RNA,RSID,SNP
Platform: unix
Platform: linux
Platform: osx
Classifier: Development Status :: 3 - Alpha
Classifier: Natural Language :: English
Classifier: Operating System :: MacOS :: MacOS X
Classifier: Operating System :: POSIX
Classifier: Operating System :: Unix
Classifier: Programming Language :: Python
Classifier: Programming Language :: Python :: 2
Classifier: Programming Language :: Python :: 2.7
Classifier: Programming Language :: Python :: 3
Classifier: Programming Language :: Python :: 3.2
Classifier: Programming Language :: Python :: 3.3
Classifier: Programming Language :: Python :: 3.4
Classifier: Programming Language :: Python :: 3.5
Classifier: Programming Language :: Python :: 3.6
Requires-Dist: cython (>=0.25)
